<fetch version="1.0" output-format="xml-platform" mapping="logical" distinct="false">
  <entity name="account">
    <attribute name="name" />
    <attribute name="primarycontactid" />
    <attribute name="telephone1" />
    <attribute name="accountid" />
    <attribute name="websiteurl" />
    <attribute name="revenue" />
    <attribute name="address1_line1" />
    <attribute name="address1_stateorprovince" />
    <attribute name="address1_city" />
    <attribute name="accountnumber" />
    <order attribute="name" descending="false" />
  </entity>
</fetch>