<?xml version="1.0" encoding="utf-8"?>
<Elements xmlns="http://schemas.microsoft.com/sharepoint/">
  <Module Name="Images">
    <File Path="Images\AppIcon.png" Url="Images/AppIcon.png" ReplaceContent="TRUE" />
    <File Path="Images\csv.png" Url="Images/csv.png" ReplaceContent="TRUE" />
    <File Path="Images\json.png" Url="Images/json.png" ReplaceContent="TRUE" />
    <File Path="Images\pdf.png" Url="Images/pdf.png" ReplaceContent="TRUE" />
    <File Path="Images\ppt.png" Url="Images/ppt.png" ReplaceContent="TRUE" />
    <File Path="Images\png.png" Url="Images/png.png" ReplaceContent="TRUE" />
    <File Path="Images\sql.png" Url="Images/sql.png" ReplaceContent="TRUE" />
    <File Path="Images\txt.png" Url="Images/txt.png" ReplaceContent="TRUE" />
    <File Path="Images\word.png" Url="Images/word.png" ReplaceContent="TRUE" />
    <File Path="Images\xls.png" Url="Images/xls.png" ReplaceContent="TRUE" />
    <File Path="Images\xml.png" Url="Images/xml.png" ReplaceContent="TRUE" />
    <File Path="Images\sort_asc.png" Url="Images/sort_asc.png" ReplaceContent="TRUE" />
    <File Path="Images\sort_asc_disabled.png" Url="Images/sort_asc_disabled.png" ReplaceContent="TRUE" />
    <File Path="Images\sort_both.png" Url="Images/sort_both.png" ReplaceContent="TRUE" />
    <File Path="Images\sort_desc.png" Url="Images/sort_desc.png" ReplaceContent="TRUE" />
    <File Path="Images\sort_desc_disabled.png" Url="Images/sort_desc_disabled.png" ReplaceContent="TRUE" />
  </Module>
</Elements>