<OutOfBrowserSettings ShortName="Contoso Moving" EnableGPUAcceleration="False" ShowInstallMenuItem="False">
  <OutOfBrowserSettings.Blurb>Contoso Moving</OutOfBrowserSettings.Blurb>
  <OutOfBrowserSettings.WindowSettings>
    <WindowSettings Title="Contoso Moving" Top="0" Left="0" WindowStartupLocation="Manual" />
  </OutOfBrowserSettings.WindowSettings>
  <OutOfBrowserSettings.SecuritySettings>
    <SecuritySettings ElevatedPermissions="Required" />
  </OutOfBrowserSettings.SecuritySettings>
  <OutOfBrowserSettings.Icons />
</OutOfBrowserSettings>